{"page":{"website":[{"id":"landing-home","domain":"website","title":"Home","path":"/","component":"LandingPage"},{"id":"menu","domain":"website","title":"Menu","path":"/menu","component":"MenuPage"},{"id":"menu-detail","domain":"website","title":"Dish","path":"/menu/:id","component":"MenuDetailPage"},{"id":"recipes","domain":"website","title":"Recipes","path":"/recipes","component":"RecipesPage"},{"id":"recipes-detail","domain":"website","title":"Recipe","path":"/recipes/:slug","component":"RecipeDetailPage"},{"id":"blog","domain":"website","title":"Blog","path":"/blog","component":"BlogPage"},{"id":"blog-detail","domain":"website","title":"Blog Post","path":"/blog/:slug","component":"BlogDetailPage"},{"id":"promotions","domain":"website","title":"Promotions","path":"/promotions","component":"PromotionsPage"},{"id":"promotions-detail","domain":"website","title":"Promotion","path":"/promotions/:id","component":"PromotionDetailPage"}],"admin":[{"id":"admin-login","domain":"admin","title":"Admin Login","path":"/admin","component":"AdminLoginPage"},{"id":"admin-dashboard","domain":"admin","title":"Admin","path":"/admin/dashboard","component":"AdminDashboardPage"}]}}
